hte/NB.py
hte/__init__.py
hte/digitize.py
hte/headers.py
hte/jsonConverting.R
hte-0.0.28.dist-info/LICENSE
hte-0.0.28.dist-info/METADATA
hte-0.0.28.dist-info/WHEEL
hte-0.0.28.dist-info/top_level.txt
hte-0.0.28.dist-info/RECORD
