Metadata-Version: 2.1
Name: hte
Version: 0.0.28
Summary: Extracting content from spesific address books
Author: Eirik Berger
Author-email: eirik.berger@gmail.com
Classifier: Programming Language :: Python :: 3
Classifier: License :: OSI Approved :: MIT License
Classifier: Operating System :: POSIX :: Linux
License-File: LICENSE
Requires-Dist: requests
Requires-Dist: PyPDF2
Requires-Dist: pdf2image
Requires-Dist: pytesseract
Requires-Dist: tesseract
Requires-Dist: tqdm
Requires-Dist: scikit-image
Requires-Dist: opencv-python
Requires-Dist: pytest-shutil
Requires-Dist: pandas
Requires-Dist: numpy
Requires-Dist: pillow
Requires-Dist: dhlab
Requires-Dist: importlib-metadata ; python_version == "3.8"
